t3qai_client/__init__.py
t3qai_client/t3qai_helper.py
t3qai_client/t3qai_serving.py
t3qai_client-1.2.3.dist-info/LICENSE-2.0.txt
t3qai_client-1.2.3.dist-info/METADATA
t3qai_client-1.2.3.dist-info/WHEEL
t3qai_client-1.2.3.dist-info/top_level.txt
t3qai_client-1.2.3.dist-info/RECORD
